djmonaco/__init__.py
djmonaco/admin.py
djmonaco/apps.py
djmonaco/forms.py
djmonaco/models.py
djmonaco/urls.py
djmonaco/views.py
djmonaco/widgets.py
djmonaco/migrations/__init__.py
djmonaco/static/css/djmonaco.css
djmonaco/static/djmonaco/monaco-editor.css
djmonaco/static/djmonaco/monaco-editor.js
djmonaco/static/js/djmonaco.js
djmonaco/templates/djmonaco/monaco.html
djmonaco/test_utils/__init__.py
djmonaco/test_utils/test_app/__init__.py
djmonaco/test_utils/test_app/admin.py
djmonaco/test_utils/test_app/apps.py
djmonaco/test_utils/test_app/models.py
djmonaco/test_utils/test_app/migrations/__init__.py
dj_monaco-1.0.4.dist-info/AUTHORS.rst
dj_monaco-1.0.4.dist-info/LICENSE
dj_monaco-1.0.4.dist-info/METADATA
dj_monaco-1.0.4.dist-info/WHEEL
dj_monaco-1.0.4.dist-info/top_level.txt
dj_monaco-1.0.4.dist-info/RECORD
