Metadata-Version: 2.1
Name: dj-monaco
Version: 1.0.4
Summary: django widget for monaco editor
Home-page: https://github.com/kverdecia/dj-monaco
Author: Karel Antonio Verdecia Ortiz
Author-email: kverdecia@gmail.com
License: MIT
Keywords: dj-monaco
Classifier: Development Status :: 5 - Production/Stable
Classifier: Framework :: Django :: 3.2
Classifier: Framework :: Django :: 4.0
Classifier: Intended Audience :: Developers
Classifier: License :: OSI Approved :: MIT License
Classifier: Natural Language :: English
Classifier: Programming Language :: Python :: 3.10
License-File: LICENSE
License-File: AUTHORS.rst
Requires-Dist: django
